[
  {
    "saves": 0,
    "goalsAgainst": 1,
    "shotsAgainst": 0,
    "player": "_JacksonBlake",
    "team": "OBO",
    "goals": 3,
    "assists": 5,
    "hits": 79,
    "touches": 152,
    "penalties": 13,
    "gamesPlayed": 4
  },
  {
    "saves": 0,
    "goalsAgainst": 0,
    "shotsAgainst": 0,
    "player": "Clifford82",
    "team": "CHC",
    "goals": 16,
    "assists": 0,
    "hits": 0,
    "touches": 451,
    "penalties": 0,
    "gamesPlayed": 2
  },
  {
    "saves": 128,
    "goalsAgainst": 15,
    "shotsAgainst": 128,
    "player": "CookieMnstr1616",
    "team": "OBO",
    "goals": 0,
    "assists": 6,
    "hits": 8,
    "touches": 113,
    "penalties": 2,
    "gamesPlayed": 6
  },
  {
    "saves": 0,
    "goalsAgainst": 0,
    "shotsAgainst": 0,
    "player": "JavonBaker",
    "team": "OBO",
    "goals": 3,
    "assists": 4,
    "hits": 12,
    "touches": 103,
    "penalties": 7,
    "gamesPlayed": 3
  },
  {
    "saves": 0,
    "goalsAgainst": 0,
    "shotsAgainst": 0,
    "player": "Kuzy_God",
    "team": "OBO",
    "goals": 3,
    "assists": 0,
    "hits": 0,
    "touches": 116,
    "penalties": 0,
    "gamesPlayed": 2
  },
  {
    "saves": 0,
    "goalsAgainst": 0,
    "shotsAgainst": 0,
    "player": "Pluds",
    "team": "OBO",
    "goals": 32,
    "assists": 5,
    "hits": 147,
    "touches": 633,
    "penalties": 16,
    "gamesPlayed": 6
  },
  {
    "saves": 121,
    "goalsAgainst": 39,
    "shotsAgainst": 121,
    "player": "rdubsss23",
    "team": "CHC",
    "goals": 1,
    "assists": 1,
    "hits": 12,
    "touches": 139,
    "penalties": 2,
    "gamesPlayed": 6
  },
  {
    "saves": 0,
    "goalsAgainst": 0,
    "shotsAgainst": 0,
    "player": "Spray_23",
    "team": "CHC",
    "goals": 1,
    "assists": 6,
    "hits": 40,
    "touches": 138,
    "penalties": 10,
    "gamesPlayed": 5
  },
  {
    "saves": 0,
    "goalsAgainst": 1,
    "shotsAgainst": 0,
    "player": "Tendy41",
    "team": "CHC",
    "goals": 11,
    "assists": 3,
    "hits": 142,
    "touches": 563,
    "penalties": 17,
    "gamesPlayed": 7
  },
  {
    "saves": 0,
    "goalsAgainst": 0,
    "shotsAgainst": 0,
    "player": "winner16",
    "team": "SSP",
    "goals": 1,
    "assists": 1,
    "hits": 0,
    "touches": 2,
    "penalties": 0,
    "gamesPlayed": 2
  },
  {
    "saves": 0,
    "goalsAgainst": 0,
    "shotsAgainst": 0,
    "player": "ZaZPxl",
    "team": "CHC",
    "goals": 2,
    "assists": 0,
    "hits": 55,
    "touches": 98,
    "penalties": 7,
    "gamesPlayed": 3
  }
]