[
  {
    "saves": 0,
    "goalsAgainst": 0,
    "shotsAgainst": 0,
    "player": "cam364",
    "team": "MTL",
    "goals": 4,
    "assists": 3,
    "hits": 96,
    "touches": 165,
    "penalties": 17,
    "gamesPlayed": 5
  },
  {
    "saves": 117,
    "goalsAgainst": 17,
    "shotsAgainst": 117,
    "player": "CookieMnstr1616",
    "team": "MTL",
    "goals": 0,
    "assists": 4,
    "hits": 5,
    "touches": 73,
    "penalties": 0,
    "gamesPlayed": 5
  },
  {
    "saves": 31,
    "goalsAgainst": 4,
    "shotsAgainst": 31,
    "player": "OnlyBirb",
    "team": "NYI",
    "goals": 1,
    "assists": 5,
    "hits": 32,
    "touches": 125,
    "penalties": 6,
    "gamesPlayed": 5
  },
  {
    "saves": 1,
    "goalsAgainst": 0,
    "shotsAgainst": 1,
    "player": "Pluds",
    "team": "NYI",
    "goals": 15,
    "assists": 1,
    "hits": 81,
    "touches": 336,
    "penalties": 7,
    "gamesPlayed": 5
  },
  {
    "saves": 13,
    "goalsAgainst": 10,
    "shotsAgainst": 13,
    "player": "rdubsss23",
    "team": "NYI",
    "goals": 0,
    "assists": 0,
    "hits": 0,
    "touches": 30,
    "penalties": 0,
    "gamesPlayed": 3
  },
  {
    "saves": 0,
    "goalsAgainst": 0,
    "shotsAgainst": 0,
    "player": "Sammythewhale",
    "team": "NYI",
    "goals": 1,
    "assists": 6,
    "hits": 42,
    "touches": 175,
    "penalties": 4,
    "gamesPlayed": 3
  },
  {
    "saves": 0,
    "goalsAgainst": 0,
    "shotsAgainst": 0,
    "player": "Tendy41",
    "team": "MTL",
    "goals": 11,
    "assists": 3,
    "hits": 107,
    "touches": 340,
    "penalties": 15,
    "gamesPlayed": 5
  },
  {
    "saves": 0,
    "goalsAgainst": 0,
    "shotsAgainst": 0,
    "player": "winner16",
    "team": "MTL",
    "goals": 0,
    "assists": 0,
    "hits": 0,
    "touches": 228,
    "penalties": 0,
    "gamesPlayed": 2
  }
]